{
    "initial_data": {
        "total_cars": 8000000,
        "total_ev": 47490,
        "total_cav": 400,
        "total_intersections": 171000,
        "total_sti": 0,
        "f_clean": 0.39
    },
    "growth_rates": {
        "cav": 0.45,
        "sti": 0.5,
        "ev": 0.07,
        "clean_energy": 0.05,
        "efficiency_doubling": 2.8,
        "total_car_increase": 0.002,
        "retire_year": 12
    },
    "consumption_rates": {
        "ecav_power": {
            "L3": {"sensing": 106, "computing": 3472, "communication": 12},
            "L4": {"sensing": 249, "computing": 6945, "communication": 17},
            "L5": {"sensing": 446, "computing": 13891, "communication": 24}
        },
        "icecav_power_factor": 1.6,
        "sti_power": {
            "Basic": {"sensing": 179, "computing": 27782, "communication": 569},
            "Semi": {"sensing": 1076, "computing": 55564, "communication": 735},
            "Highly": {"sensing": 1417, "computing": 111129, "communication": 884}
        },
        "cav_levels": [0.5, 0.333, 0.167],
        "sti_levels": [0.5, 0.333, 0.167]
    },
    "emission_factors": {
        "e_clean": 0.03,
        "e_fossil": 0.5,
        "e_gasoline": 1.65
    }
}